mcp_supervisor_squad/__init__.py
mcp_supervisor_squad/cli.py
mcp_supervisor_squad/persistence/__init__.py
mcp_supervisor_squad/persistence/state.py
mcp_supervisor_squad/persistence/storage.py
mcp_supervisor_squad/planning/__init__.py
mcp_supervisor_squad/planning/config.py
mcp_supervisor_squad/planning/contract.py
mcp_supervisor_squad/planning/decider.py
mcp_supervisor_squad/runtime/__init__.py
mcp_supervisor_squad/runtime/dispatch.py
mcp_supervisor_squad/runtime/worker.py
mcp_supervisor_squad/server.py
mcp_supervisor_squad/utils/__init__.py
mcp_supervisor_squad/utils/constants.py
mcp_supervisor_squad/utils/patch_utils.py
mcp_supervisor_squad/utils/path.py
mcp_supervisor_squad/utils/storage.py
mcp_supervisor_squad/utils/time.py
mcp_supervisor_squad-0.1.52.dist-info/METADATA
mcp_supervisor_squad-0.1.52.dist-info/WHEEL
mcp_supervisor_squad-0.1.52.dist-info/entry_points.txt
mcp_supervisor_squad-0.1.52.dist-info/RECORD
