Metadata-Version: 2.4
Name: mcp-supervisor-squad
Version: 0.1.52
Summary: MCP server for the supervisor-squad workflow.
Author: Codex Agent
Author-email: agent@example.com
Requires-Python: >=3.11,<4.0
Classifier: Programming Language :: Python :: 3
Classifier: Programming Language :: Python :: 3.11
Classifier: Programming Language :: Python :: 3.12
Classifier: Programming Language :: Python :: 3.13
Classifier: Programming Language :: Python :: 3.14
Requires-Dist: fastmcp (>=0.3.0,<0.4.0)
Requires-Dist: mcp (==1.25.0)
